join_agent/__init__.py
join_agent/agent.py
join_agent/config.py
join_agent/constants.py
join_agent/models.py
join_agent-0.1.3.dist-info/METADATA
join_agent-0.1.3.dist-info/WHEEL
join_agent-0.1.3.dist-info/top_level.txt
join_agent-0.1.3.dist-info/RECORD
