Metadata-Version: 2.4
Name: join-agent
Version: 0.1.3
Summary: LLM-driven intelligent join key suggestion agent
Author-email: StepFunction AI <team@stepfunction.ai>
Maintainer-email: StepFunction AI <team@stepfunction.ai>
License-Expression: MIT
Project-URL: Homepage, https://github.com/stepfnAI/join_agent
Project-URL: Issues, https://github.com/stepfnAI/join_agent/issues
Requires-Python: >=3.10
Requires-Dist: sfn-blueprint>=0.6.6
Requires-Dist: pandas
Requires-Dist: pydantic-settings
Provides-Extra: dev
Requires-Dist: pytest>=7.0.0; extra == "dev"
Requires-Dist: pytest-cov>=4.0.0; extra == "dev"
Requires-Dist: black>=23.0.0; extra == "dev"
Requires-Dist: flake8>=6.0.0; extra == "dev"
Requires-Dist: mypy>=1.0.0; extra == "dev"
